oj/__init__.py
oj-0.0.4.dist-info/LICENSE
oj-0.0.4.dist-info/METADATA
oj-0.0.4.dist-info/WHEEL
oj-0.0.4.dist-info/top_level.txt
oj-0.0.4.dist-info/RECORD
