Metadata-Version: 2.1
Name: oj
Version: 0.0.4
Summary: Reading excel (but more than just cell values: Also colors
Home-page: https://github.com/thorwhalen/uu/tree/master/oj
Author: Thor Whalen
License: apache-2.0
Platform: any
License-File: LICENSE
